setup.py
contactstudiolib/__init__.py
contactstudiolib/avatar.py
contactstudiolib/cds.py
contactstudiolib.egg-info/PKG-INFO
contactstudiolib.egg-info/SOURCES.txt
contactstudiolib.egg-info/dependency_links.txt
contactstudiolib.egg-info/not-zip-safe
contactstudiolib.egg-info/requires.txt
contactstudiolib.egg-info/top_level.txt