Metadata-Version: 1.1
Name: contactstudiolib
Version: 0.1
Summary: Pacote de exemplo do curso na G$
Home-page: https://github.com/renzon/contact-studio
Author: Renzo Nuccitelli
Author-email: renzo.n@gmail.com
License: BSD
Platform: UNKNOWN
Classifier: Development Status :: 4 - Beta
Classifier: Environment :: Web Environment
Classifier: Intended Audience :: Developers
Classifier: License :: OSI Approved :: BSD License
Classifier: Operating System :: OS Independent
Classifier: Programming Language :: Python
Classifier: Framework :: Paste
